{
  "meta": {
    "timestamp": "2026-04-09T21:19:00.680Z",
    "source": "Steam Community Market",
    "currency": "EUR",
    "scraped": 2,
    "requested": 50,
    "errors": 48,
    "concurrency": 2
  },
  "map": {
    "Stockholm 2021 Challengers Sticker Capsule": {
      "fetchedAt": "2026-04-09T21:19:00.430Z",
      "listingUrl": "https://steamcommunity.com/market/listings/730/Stockholm%202021%20Challengers%20Sticker%20Capsule",
      "itemNameId": "176272161",
      "overview": {
        "lowestPriceEur": 3.99,
        "medianPriceEur": 4.635,
        "volume": null,
        "failed": true,
        "statusCode": 429
      },
      "summary": {
        "latestPriceEur": 4.635,
        "change7dPct": 0.9144350097975139,
        "change30dPct": -0.6217838765008558,
        "change90dPct": -0.3868471953578293,
        "low30dEur": 4.289,
        "high30dEur": 4.719,
        "avgVolume30d": 7.633333333333334,
        "volatility30dPct": 24.21497890491189,
        "spark": [
          4.62,
          4.601,
          4.642,
          4.649,
          4.719,
          4.684,
          4.294,
          4.65,
          4.647,
          4.289,
          4.614,
          4.607,
          4.587,
          4.6,
          4.591,
          4.592,
          4.591,
          4.593,
          4.593,
          4.602,
          4.365,
          4.33,
          4.62,
          4.635
        ]
      },
      "history": [
        {
          "label": "Mar 30 2026 11: +0",
          "date": "2026-03-30T00:00:00.000Z",
          "price": 4.73,
          "volume": 2
        },
        {
          "label": "Mar 30 2026 12: +0",
          "date": "2026-03-30T00:00:00.000Z",
          "price": 4.73,
          "volume": 9
        },
        {
          "label": "Mar 30 2026 14: +0",
          "date": "2026-03-30T00:00:00.000Z",
          "price": 4.678,
          "volume": 2
        },
        {
          "label": "Mar 30 2026 16: +0",
          "date": "2026-03-30T00:00:00.000Z",
          "price": 4.679,
          "volume": 1
        },
        {
          "label": "Mar 30 2026 17: +0",
          "date": "2026-03-30T00:00:00.000Z",
          "price": 4.69,
          "volume": 1
        },
        {
          "label": "Mar 30 2026 20: +0",
          "date": "2026-03-30T00:00:00.000Z",
          "price": 4.68,
          "volume": 9
        },
        {
          "label": "Mar 30 2026 21: +0",
          "date": "2026-03-30T00:00:00.000Z",
          "price": 4.659,
          "volume": 9
        },
        {
          "label": "Mar 30 2026 23: +0",
          "date": "2026-03-30T00:00:00.000Z",
          "price": 4.67,
          "volume": 12
        },
        {
          "label": "Mar 31 2026 01: +0",
          "date": "2026-03-31T00:00:00.000Z",
          "price": 4.499,
          "volume": 1
        },
        {
          "label": "Mar 31 2026 02: +0",
          "date": "2026-03-31T00:00:00.000Z",
          "price": 4.67,
          "volume": 7
        },
        {
          "label": "Mar 31 2026 03: +0",
          "date": "2026-03-31T00:00:00.000Z",
          "price": 4.694,
          "volume": 2
        },
        {
          "label": "Mar 31 2026 04: +0",
          "date": "2026-03-31T00:00:00.000Z",
          "price": 4.71,
          "volume": 3
        },
        {
          "label": "Mar 31 2026 05: +0",
          "date": "2026-03-31T00:00:00.000Z",
          "price": 4.67,
          "volume": 1
        },
        {
          "label": "Mar 31 2026 07: +0",
          "date": "2026-03-31T00:00:00.000Z",
          "price": 4.71,
          "volume": 3
        },
        {
          "label": "Mar 31 2026 08: +0",
          "date": "2026-03-31T00:00:00.000Z",
          "price": 4.716,
          "volume": 1
        },
        {
          "label": "Mar 31 2026 09: +0",
          "date": "2026-03-31T00:00:00.000Z",
          "price": 4.71,
          "volume": 2
        },
        {
          "label": "Mar 31 2026 12: +0",
          "date": "2026-03-31T00:00:00.000Z",
          "price": 4.725,
          "volume": 11
        },
        {
          "label": "Mar 31 2026 13: +0",
          "date": "2026-03-31T00:00:00.000Z",
          "price": 4.71,
          "volume": 7
        },
        {
          "label": "Mar 31 2026 14: +0",
          "date": "2026-03-31T00:00:00.000Z",
          "price": 4.71,
          "volume": 2
        },
        {
          "label": "Mar 31 2026 17: +0",
          "date": "2026-03-31T00:00:00.000Z",
          "price": 4.694,
          "volume": 2
        },
        {
          "label": "Mar 31 2026 18: +0",
          "date": "2026-03-31T00:00:00.000Z",
          "price": 4.71,
          "volume": 5
        },
        {
          "label": "Mar 31 2026 19: +0",
          "date": "2026-03-31T00:00:00.000Z",
          "price": 4.694,
          "volume": 24
        },
        {
          "label": "Mar 31 2026 20: +0",
          "date": "2026-03-31T00:00:00.000Z",
          "price": 4.71,
          "volume": 1
        },
        {
          "label": "Mar 31 2026 22: +0",
          "date": "2026-03-31T00:00:00.000Z",
          "price": 4.425,
          "volume": 6
        },
        {
          "label": "Mar 31 2026 23: +0",
          "date": "2026-03-31T00:00:00.000Z",
          "price": 4.67,
          "volume": 1
        },
        {
          "label": "Apr 01 2026 00: +0",
          "date": "2026-04-01T00:00:00.000Z",
          "price": 4.672,
          "volume": 8
        },
        {
          "label": "Apr 01 2026 01: +0",
          "date": "2026-04-01T00:00:00.000Z",
          "price": 4.672,
          "volume": 20
        },
        {
          "label": "Apr 01 2026 03: +0",
          "date": "2026-04-01T00:00:00.000Z",
          "price": 4.661,
          "volume": 3
        },
        {
          "label": "Apr 01 2026 04: +0",
          "date": "2026-04-01T00:00:00.000Z",
          "price": 4.672,
          "volume": 3
        },
        {
          "label": "Apr 01 2026 05: +0",
          "date": "2026-04-01T00:00:00.000Z",
          "price": 4.672,
          "volume": 1
        },
        {
          "label": "Apr 01 2026 07: +0",
          "date": "2026-04-01T00:00:00.000Z",
          "price": 4.67,
          "volume": 2
        },
        {
          "label": "Apr 01 2026 12: +0",
          "date": "2026-04-01T00:00:00.000Z",
          "price": 4.641,
          "volume": 4
        },
        {
          "label": "Apr 01 2026 13: +0",
          "date": "2026-04-01T00:00:00.000Z",
          "price": 4.662,
          "volume": 2
        },
        {
          "label": "Apr 01 2026 14: +0",
          "date": "2026-04-01T00:00:00.000Z",
          "price": 4.645,
          "volume": 2
        },
        {
          "label": "Apr 01 2026 15: +0",
          "date": "2026-04-01T00:00:00.000Z",
          "price": 4.66,
          "volume": 2
        },
        {
          "label": "Apr 01 2026 17: +0",
          "date": "2026-04-01T00:00:00.000Z",
          "price": 4.677,
          "volume": 1
        },
        {
          "label": "Apr 01 2026 18: +0",
          "date": "2026-04-01T00:00:00.000Z",
          "price": 4.645,
          "volume": 7
        },
        {
          "label": "Apr 01 2026 19: +0",
          "date": "2026-04-01T00:00:00.000Z",
          "price": 4.638,
          "volume": 2
        },
        {
          "label": "Apr 01 2026 20: +0",
          "date": "2026-04-01T00:00:00.000Z",
          "price": 4.634,
          "volume": 3
        },
        {
          "label": "Apr 01 2026 21: +0",
          "date": "2026-04-01T00:00:00.000Z",
          "price": 4.715,
          "volume": 1
        },
        {
          "label": "Apr 01 2026 22: +0",
          "date": "2026-04-01T00:00:00.000Z",
          "price": 4.691,
          "volume": 1
        },
        {
          "label": "Apr 01 2026 23: +0",
          "date": "2026-04-01T00:00:00.000Z",
          "price": 4.688,
          "volume": 1
        },
        {
          "label": "Apr 02 2026 02: +0",
          "date": "2026-04-02T00:00:00.000Z",
          "price": 4.68,
          "volume": 4
        },
        {
          "label": "Apr 02 2026 09: +0",
          "date": "2026-04-02T00:00:00.000Z",
          "price": 4.642,
          "volume": 2
        },
        {
          "label": "Apr 02 2026 11: +0",
          "date": "2026-04-02T00:00:00.000Z",
          "price": 4.62,
          "volume": 4
        },
        {
          "label": "Apr 02 2026 12: +0",
          "date": "2026-04-02T00:00:00.000Z",
          "price": 4.646,
          "volume": 21
        },
        {
          "label": "Apr 02 2026 13: +0",
          "date": "2026-04-02T00:00:00.000Z",
          "price": 4.707,
          "volume": 6
        },
        {
          "label": "Apr 02 2026 14: +0",
          "date": "2026-04-02T00:00:00.000Z",
          "price": 4.712,
          "volume": 2
        },
        {
          "label": "Apr 02 2026 15: +0",
          "date": "2026-04-02T00:00:00.000Z",
          "price": 4.29,
          "volume": 1
        },
        {
          "label": "Apr 02 2026 16: +0",
          "date": "2026-04-02T00:00:00.000Z",
          "price": 4.711,
          "volume": 2
        },
        {
          "label": "Apr 02 2026 17: +0",
          "date": "2026-04-02T00:00:00.000Z",
          "price": 4.712,
          "volume": 3
        },
        {
          "label": "Apr 02 2026 18: +0",
          "date": "2026-04-02T00:00:00.000Z",
          "price": 4.696,
          "volume": 6
        },
        {
          "label": "Apr 02 2026 19: +0",
          "date": "2026-04-02T00:00:00.000Z",
          "price": 4.62,
          "volume": 5
        },
        {
          "label": "Apr 02 2026 20: +0",
          "date": "2026-04-02T00:00:00.000Z",
          "price": 4.69,
          "volume": 10
        },
        {
          "label": "Apr 02 2026 21: +0",
          "date": "2026-04-02T00:00:00.000Z",
          "price": 4.69,
          "volume": 4
        },
        {
          "label": "Apr 02 2026 23: +0",
          "date": "2026-04-02T00:00:00.000Z",
          "price": 4.67,
          "volume": 16
        },
        {
          "label": "Apr 03 2026 00: +0",
          "date": "2026-04-03T00:00:00.000Z",
          "price": 4.677,
          "volume": 3
        },
        {
          "label": "Apr 03 2026 01: +0",
          "date": "2026-04-03T00:00:00.000Z",
          "price": 4.676,
          "volume": 2
        },
        {
          "label": "Apr 03 2026 03: +0",
          "date": "2026-04-03T00:00:00.000Z",
          "price": 4.67,
          "volume": 16
        },
        {
          "label": "Apr 03 2026 06: +0",
          "date": "2026-04-03T00:00:00.000Z",
          "price": 4.677,
          "volume": 4
        },
        {
          "label": "Apr 03 2026 07: +0",
          "date": "2026-04-03T00:00:00.000Z",
          "price": 4.677,
          "volume": 10
        },
        {
          "label": "Apr 03 2026 08: +0",
          "date": "2026-04-03T00:00:00.000Z",
          "price": 4.61,
          "volume": 4
        },
        {
          "label": "Apr 03 2026 09: +0",
          "date": "2026-04-03T00:00:00.000Z",
          "price": 4.642,
          "volume": 2
        },
        {
          "label": "Apr 03 2026 10: +0",
          "date": "2026-04-03T00:00:00.000Z",
          "price": 4.676,
          "volume": 4
        },
        {
          "label": "Apr 03 2026 11: +0",
          "date": "2026-04-03T00:00:00.000Z",
          "price": 4.614,
          "volume": 1
        },
        {
          "label": "Apr 03 2026 12: +0",
          "date": "2026-04-03T00:00:00.000Z",
          "price": 4.659,
          "volume": 3
        },
        {
          "label": "Apr 03 2026 13: +0",
          "date": "2026-04-03T00:00:00.000Z",
          "price": 4.66,
          "volume": 10
        },
        {
          "label": "Apr 03 2026 14: +0",
          "date": "2026-04-03T00:00:00.000Z",
          "price": 4.655,
          "volume": 13
        },
        {
          "label": "Apr 03 2026 15: +0",
          "date": "2026-04-03T00:00:00.000Z",
          "price": 4.66,
          "volume": 18
        },
        {
          "label": "Apr 03 2026 16: +0",
          "date": "2026-04-03T00:00:00.000Z",
          "price": 4.66,
          "volume": 1
        },
        {
          "label": "Apr 03 2026 17: +0",
          "date": "2026-04-03T00:00:00.000Z",
          "price": 4.66,
          "volume": 1
        },
        {
          "label": "Apr 03 2026 18: +0",
          "date": "2026-04-03T00:00:00.000Z",
          "price": 4.66,
          "volume": 3
        },
        {
          "label": "Apr 03 2026 19: +0",
          "date": "2026-04-03T00:00:00.000Z",
          "price": 4.655,
          "volume": 1
        },
        {
          "label": "Apr 03 2026 22: +0",
          "date": "2026-04-03T00:00:00.000Z",
          "price": 4.683,
          "volume": 6
        },
        {
          "label": "Apr 03 2026 23: +0",
          "date": "2026-04-03T00:00:00.000Z",
          "price": 4.669,
          "volume": 1
        },
        {
          "label": "Apr 04 2026 00: +0",
          "date": "2026-04-04T00:00:00.000Z",
          "price": 4.67,
          "volume": 4
        },
        {
          "label": "Apr 04 2026 01: +0",
          "date": "2026-04-04T00:00:00.000Z",
          "price": 4.671,
          "volume": 22
        },
        {
          "label": "Apr 04 2026 02: +0",
          "date": "2026-04-04T00:00:00.000Z",
          "price": 4.658,
          "volume": 13
        },
        {
          "label": "Apr 04 2026 03: +0",
          "date": "2026-04-04T00:00:00.000Z",
          "price": 4.67,
          "volume": 2
        },
        {
          "label": "Apr 04 2026 04: +0",
          "date": "2026-04-04T00:00:00.000Z",
          "price": 4.67,
          "volume": 1
        },
        {
          "label": "Apr 04 2026 05: +0",
          "date": "2026-04-04T00:00:00.000Z",
          "price": 4.67,
          "volume": 2
        },
        {
          "label": "Apr 04 2026 06: +0",
          "date": "2026-04-04T00:00:00.000Z",
          "price": 4.67,
          "volume": 2
        },
        {
          "label": "Apr 04 2026 08: +0",
          "date": "2026-04-04T00:00:00.000Z",
          "price": 4.671,
          "volume": 7
        },
        {
          "label": "Apr 04 2026 09: +0",
          "date": "2026-04-04T00:00:00.000Z",
          "price": 4.671,
          "volume": 7
        },
        {
          "label": "Apr 04 2026 10: +0",
          "date": "2026-04-04T00:00:00.000Z",
          "price": 4.486,
          "volume": 2
        },
        {
          "label": "Apr 04 2026 11: +0",
          "date": "2026-04-04T00:00:00.000Z",
          "price": 4.282,
          "volume": 2
        },
        {
          "label": "Apr 04 2026 12: +0",
          "date": "2026-04-04T00:00:00.000Z",
          "price": 4.626,
          "volume": 4
        },
        {
          "label": "Apr 04 2026 13: +0",
          "date": "2026-04-04T00:00:00.000Z",
          "price": 4.669,
          "volume": 4
        },
        {
          "label": "Apr 04 2026 14: +0",
          "date": "2026-04-04T00:00:00.000Z",
          "price": 4.667,
          "volume": 11
        },
        {
          "label": "Apr 04 2026 15: +0",
          "date": "2026-04-04T00:00:00.000Z",
          "price": 4.666,
          "volume": 34
        },
        {
          "label": "Apr 04 2026 16: +0",
          "date": "2026-04-04T00:00:00.000Z",
          "price": 4.653,
          "volume": 2
        },
        {
          "label": "Apr 04 2026 17: +0",
          "date": "2026-04-04T00:00:00.000Z",
          "price": 4.662,
          "volume": 2
        },
        {
          "label": "Apr 04 2026 18: +0",
          "date": "2026-04-04T00:00:00.000Z",
          "price": 4.667,
          "volume": 1
        },
        {
          "label": "Apr 04 2026 20: +0",
          "date": "2026-04-04T00:00:00.000Z",
          "price": 4.611,
          "volume": 1
        },
        {
          "label": "Apr 04 2026 21: +0",
          "date": "2026-04-04T00:00:00.000Z",
          "price": 4.612,
          "volume": 5
        },
        {
          "label": "Apr 04 2026 22: +0",
          "date": "2026-04-04T00:00:00.000Z",
          "price": 4.623,
          "volume": 1
        },
        {
          "label": "Apr 05 2026 00: +0",
          "date": "2026-04-05T00:00:00.000Z",
          "price": 4.63,
          "volume": 8
        },
        {
          "label": "Apr 05 2026 01: +0",
          "date": "2026-04-05T00:00:00.000Z",
          "price": 4.671,
          "volume": 72
        },
        {
          "label": "Apr 05 2026 02: +0",
          "date": "2026-04-05T00:00:00.000Z",
          "price": 4.671,
          "volume": 3
        },
        {
          "label": "Apr 05 2026 03: +0",
          "date": "2026-04-05T00:00:00.000Z",
          "price": 4.67,
          "volume": 3
        },
        {
          "label": "Apr 05 2026 04: +0",
          "date": "2026-04-05T00:00:00.000Z",
          "price": 4.67,
          "volume": 10
        },
        {
          "label": "Apr 05 2026 07: +0",
          "date": "2026-04-05T00:00:00.000Z",
          "price": 4.674,
          "volume": 4
        },
        {
          "label": "Apr 05 2026 08: +0",
          "date": "2026-04-05T00:00:00.000Z",
          "price": 4.669,
          "volume": 2
        },
        {
          "label": "Apr 05 2026 09: +0",
          "date": "2026-04-05T00:00:00.000Z",
          "price": 4.669,
          "volume": 2
        },
        {
          "label": "Apr 05 2026 10: +0",
          "date": "2026-04-05T00:00:00.000Z",
          "price": 4.479,
          "volume": 4
        },
        {
          "label": "Apr 05 2026 11: +0",
          "date": "2026-04-05T00:00:00.000Z",
          "price": 4.645,
          "volume": 2
        },
        {
          "label": "Apr 05 2026 12: +0",
          "date": "2026-04-05T00:00:00.000Z",
          "price": 4.67,
          "volume": 3
        },
        {
          "label": "Apr 05 2026 13: +0",
          "date": "2026-04-05T00:00:00.000Z",
          "price": 4.67,
          "volume": 2
        },
        {
          "label": "Apr 05 2026 14: +0",
          "date": "2026-04-05T00:00:00.000Z",
          "price": 4.67,
          "volume": 4
        },
        {
          "label": "Apr 05 2026 16: +0",
          "date": "2026-04-05T00:00:00.000Z",
          "price": 4.66,
          "volume": 2
        },
        {
          "label": "Apr 05 2026 17: +0",
          "date": "2026-04-05T00:00:00.000Z",
          "price": 4.696,
          "volume": 1
        },
        {
          "label": "Apr 05 2026 18: +0",
          "date": "2026-04-05T00:00:00.000Z",
          "price": 4.381,
          "volume": 1
        },
        {
          "label": "Apr 05 2026 21: +0",
          "date": "2026-04-05T00:00:00.000Z",
          "price": 4.671,
          "volume": 121
        },
        {
          "label": "Apr 05 2026 22: +0",
          "date": "2026-04-05T00:00:00.000Z",
          "price": 4.671,
          "volume": 31
        },
        {
          "label": "Apr 05 2026 23: +0",
          "date": "2026-04-05T00:00:00.000Z",
          "price": 4.665,
          "volume": 2
        },
        {
          "label": "Apr 06 2026 00: +0",
          "date": "2026-04-06T00:00:00.000Z",
          "price": 4.671,
          "volume": 2
        },
        {
          "label": "Apr 06 2026 01: +0",
          "date": "2026-04-06T00:00:00.000Z",
          "price": 4.669,
          "volume": 2
        },
        {
          "label": "Apr 06 2026 05: +0",
          "date": "2026-04-06T00:00:00.000Z",
          "price": 4.671,
          "volume": 3
        },
        {
          "label": "Apr 06 2026 09: +0",
          "date": "2026-04-06T00:00:00.000Z",
          "price": 4.65,
          "volume": 4
        },
        {
          "label": "Apr 06 2026 10: +0",
          "date": "2026-04-06T00:00:00.000Z",
          "price": 4.669,
          "volume": 3
        },
        {
          "label": "Apr 06 2026 11: +0",
          "date": "2026-04-06T00:00:00.000Z",
          "price": 4.669,
          "volume": 13
        },
        {
          "label": "Apr 06 2026 12: +0",
          "date": "2026-04-06T00:00:00.000Z",
          "price": 4.669,
          "volume": 3
        },
        {
          "label": "Apr 06 2026 13: +0",
          "date": "2026-04-06T00:00:00.000Z",
          "price": 4.669,
          "volume": 8
        },
        {
          "label": "Apr 06 2026 15: +0",
          "date": "2026-04-06T00:00:00.000Z",
          "price": 4.678,
          "volume": 2
        },
        {
          "label": "Apr 06 2026 16: +0",
          "date": "2026-04-06T00:00:00.000Z",
          "price": 4.669,
          "volume": 1
        },
        {
          "label": "Apr 06 2026 17: +0",
          "date": "2026-04-06T00:00:00.000Z",
          "price": 4.682,
          "volume": 2
        },
        {
          "label": "Apr 06 2026 18: +0",
          "date": "2026-04-06T00:00:00.000Z",
          "price": 4.696,
          "volume": 7
        },
        {
          "label": "Apr 06 2026 19: +0",
          "date": "2026-04-06T00:00:00.000Z",
          "price": 4.669,
          "volume": 7
        },
        {
          "label": "Apr 06 2026 20: +0",
          "date": "2026-04-06T00:00:00.000Z",
          "price": 4.696,
          "volume": 7
        },
        {
          "label": "Apr 06 2026 21: +0",
          "date": "2026-04-06T00:00:00.000Z",
          "price": 4.685,
          "volume": 4
        },
        {
          "label": "Apr 06 2026 23: +0",
          "date": "2026-04-06T00:00:00.000Z",
          "price": 4.637,
          "volume": 1
        },
        {
          "label": "Apr 07 2026 01: +0",
          "date": "2026-04-07T00:00:00.000Z",
          "price": 4.596,
          "volume": 10
        },
        {
          "label": "Apr 07 2026 02: +0",
          "date": "2026-04-07T00:00:00.000Z",
          "price": 4.638,
          "volume": 6
        },
        {
          "label": "Apr 07 2026 05: +0",
          "date": "2026-04-07T00:00:00.000Z",
          "price": 4.672,
          "volume": 2
        },
        {
          "label": "Apr 07 2026 09: +0",
          "date": "2026-04-07T00:00:00.000Z",
          "price": 4.609,
          "volume": 1
        },
        {
          "label": "Apr 07 2026 11: +0",
          "date": "2026-04-07T00:00:00.000Z",
          "price": 4.309,
          "volume": 46
        },
        {
          "label": "Apr 07 2026 12: +0",
          "date": "2026-04-07T00:00:00.000Z",
          "price": 4.21,
          "volume": 128
        },
        {
          "label": "Apr 07 2026 13: +0",
          "date": "2026-04-07T00:00:00.000Z",
          "price": 4.66,
          "volume": 11
        },
        {
          "label": "Apr 07 2026 14: +0",
          "date": "2026-04-07T00:00:00.000Z",
          "price": 4.684,
          "volume": 2
        },
        {
          "label": "Apr 07 2026 16: +0",
          "date": "2026-04-07T00:00:00.000Z",
          "price": 4.685,
          "volume": 8
        },
        {
          "label": "Apr 07 2026 17: +0",
          "date": "2026-04-07T00:00:00.000Z",
          "price": 4.621,
          "volume": 1
        },
        {
          "label": "Apr 07 2026 18: +0",
          "date": "2026-04-07T00:00:00.000Z",
          "price": 4.23,
          "volume": 4
        },
        {
          "label": "Apr 07 2026 19: +0",
          "date": "2026-04-07T00:00:00.000Z",
          "price": 4.238,
          "volume": 4
        },
        {
          "label": "Apr 07 2026 20: +0",
          "date": "2026-04-07T00:00:00.000Z",
          "price": 4.68,
          "volume": 3
        },
        {
          "label": "Apr 07 2026 21: +0",
          "date": "2026-04-07T00:00:00.000Z",
          "price": 4.68,
          "volume": 4
        },
        {
          "label": "Apr 07 2026 22: +0",
          "date": "2026-04-07T00:00:00.000Z",
          "price": 4.693,
          "volume": 1
        },
        {
          "label": "Apr 08 2026 00: +0",
          "date": "2026-04-08T00:00:00.000Z",
          "price": 4.59,
          "volume": 3
        },
        {
          "label": "Apr 08 2026 01: +0",
          "date": "2026-04-08T00:00:00.000Z",
          "price": 4.682,
          "volume": 3
        },
        {
          "label": "Apr 08 2026 05: +0",
          "date": "2026-04-08T00:00:00.000Z",
          "price": 4.664,
          "volume": 1
        },
        {
          "label": "Apr 08 2026 09: +0",
          "date": "2026-04-08T00:00:00.000Z",
          "price": 4.659,
          "volume": 2
        },
        {
          "label": "Apr 08 2026 10: +0",
          "date": "2026-04-08T00:00:00.000Z",
          "price": 4.664,
          "volume": 7
        },
        {
          "label": "Apr 08 2026 11: +0",
          "date": "2026-04-08T00:00:00.000Z",
          "price": 4.663,
          "volume": 13
        },
        {
          "label": "Apr 08 2026 12: +0",
          "date": "2026-04-08T00:00:00.000Z",
          "price": 4.66,
          "volume": 9
        },
        {
          "label": "Apr 08 2026 13: +0",
          "date": "2026-04-08T00:00:00.000Z",
          "price": 4.645,
          "volume": 12
        },
        {
          "label": "Apr 08 2026 14: +0",
          "date": "2026-04-08T00:00:00.000Z",
          "price": 4.686,
          "volume": 14
        },
        {
          "label": "Apr 08 2026 15: +0",
          "date": "2026-04-08T00:00:00.000Z",
          "price": 4.64,
          "volume": 4
        },
        {
          "label": "Apr 08 2026 17: +0",
          "date": "2026-04-08T00:00:00.000Z",
          "price": 4.62,
          "volume": 2
        },
        {
          "label": "Apr 08 2026 18: +0",
          "date": "2026-04-08T00:00:00.000Z",
          "price": 4.601,
          "volume": 4
        },
        {
          "label": "Apr 08 2026 19: +0",
          "date": "2026-04-08T00:00:00.000Z",
          "price": 4.642,
          "volume": 6
        },
        {
          "label": "Apr 08 2026 20: +0",
          "date": "2026-04-08T00:00:00.000Z",
          "price": 4.649,
          "volume": 9
        },
        {
          "label": "Apr 08 2026 21: +0",
          "date": "2026-04-08T00:00:00.000Z",
          "price": 4.719,
          "volume": 3
        },
        {
          "label": "Apr 08 2026 22: +0",
          "date": "2026-04-08T00:00:00.000Z",
          "price": 4.684,
          "volume": 3
        },
        {
          "label": "Apr 08 2026 23: +0",
          "date": "2026-04-08T00:00:00.000Z",
          "price": 4.294,
          "volume": 3
        },
        {
          "label": "Apr 09 2026 00: +0",
          "date": "2026-04-09T00:00:00.000Z",
          "price": 4.65,
          "volume": 34
        },
        {
          "label": "Apr 09 2026 02: +0",
          "date": "2026-04-09T00:00:00.000Z",
          "price": 4.647,
          "volume": 1
        },
        {
          "label": "Apr 09 2026 04: +0",
          "date": "2026-04-09T00:00:00.000Z",
          "price": 4.289,
          "volume": 1
        },
        {
          "label": "Apr 09 2026 07: +0",
          "date": "2026-04-09T00:00:00.000Z",
          "price": 4.614,
          "volume": 1
        },
        {
          "label": "Apr 09 2026 08: +0",
          "date": "2026-04-09T00:00:00.000Z",
          "price": 4.607,
          "volume": 1
        },
        {
          "label": "Apr 09 2026 09: +0",
          "date": "2026-04-09T00:00:00.000Z",
          "price": 4.587,
          "volume": 8
        },
        {
          "label": "Apr 09 2026 10: +0",
          "date": "2026-04-09T00:00:00.000Z",
          "price": 4.6,
          "volume": 5
        },
        {
          "label": "Apr 09 2026 12: +0",
          "date": "2026-04-09T00:00:00.000Z",
          "price": 4.591,
          "volume": 12
        },
        {
          "label": "Apr 09 2026 13: +0",
          "date": "2026-04-09T00:00:00.000Z",
          "price": 4.592,
          "volume": 23
        },
        {
          "label": "Apr 09 2026 14: +0",
          "date": "2026-04-09T00:00:00.000Z",
          "price": 4.591,
          "volume": 7
        },
        {
          "label": "Apr 09 2026 15: +0",
          "date": "2026-04-09T00:00:00.000Z",
          "price": 4.593,
          "volume": 1
        },
        {
          "label": "Apr 09 2026 16: +0",
          "date": "2026-04-09T00:00:00.000Z",
          "price": 4.593,
          "volume": 1
        },
        {
          "label": "Apr 09 2026 17: +0",
          "date": "2026-04-09T00:00:00.000Z",
          "price": 4.602,
          "volume": 3
        },
        {
          "label": "Apr 09 2026 18: +0",
          "date": "2026-04-09T00:00:00.000Z",
          "price": 4.365,
          "volume": 7
        },
        {
          "label": "Apr 09 2026 19: +0",
          "date": "2026-04-09T00:00:00.000Z",
          "price": 4.33,
          "volume": 13
        },
        {
          "label": "Apr 09 2026 20: +0",
          "date": "2026-04-09T00:00:00.000Z",
          "price": 4.62,
          "volume": 17
        },
        {
          "label": "Apr 09 2026 21: +0",
          "date": "2026-04-09T00:00:00.000Z",
          "price": 4.635,
          "volume": 5
        }
      ]
    },
    "Stockholm 2021 Contenders Sticker Capsule": {
      "fetchedAt": "2026-04-09T21:19:00.680Z",
      "listingUrl": "https://steamcommunity.com/market/listings/730/Stockholm%202021%20Contenders%20Sticker%20Capsule",
      "itemNameId": "176272159",
      "overview": {
        "lowestPriceEur": 3.15,
        "medianPriceEur": 3.51,
        "volume": null,
        "failed": true,
        "statusCode": 429
      },
      "summary": {
        "latestPriceEur": 3.51,
        "change7dPct": -5.083829096809091,
        "change30dPct": -4.5157780195865165,
        "change90dPct": -3.1189621860336856,
        "low30dEur": 3.4,
        "high30dEur": 3.725,
        "avgVolume30d": 8.366666666666667,
        "volatility30dPct": 26.279021016297264,
        "spark": [
          3.66,
          3.642,
          3.584,
          3.676,
          3.656,
          3.492,
          3.403,
          3.642,
          3.653,
          3.669,
          3.725,
          3.7,
          3.7,
          3.521,
          3.694,
          3.698,
          3.698,
          3.698,
          3.4,
          3.408,
          3.699,
          3.7,
          3.51,
          3.51
        ]
      },
      "history": [
        {
          "label": "Mar 31 2026 01: +0",
          "date": "2026-03-31T00:00:00.000Z",
          "price": 3.618,
          "volume": 4
        },
        {
          "label": "Mar 31 2026 02: +0",
          "date": "2026-03-31T00:00:00.000Z",
          "price": 3.61,
          "volume": 8
        },
        {
          "label": "Mar 31 2026 04: +0",
          "date": "2026-03-31T00:00:00.000Z",
          "price": 3.61,
          "volume": 1
        },
        {
          "label": "Mar 31 2026 08: +0",
          "date": "2026-03-31T00:00:00.000Z",
          "price": 3.616,
          "volume": 6
        },
        {
          "label": "Mar 31 2026 09: +0",
          "date": "2026-03-31T00:00:00.000Z",
          "price": 3.629,
          "volume": 1
        },
        {
          "label": "Mar 31 2026 12: +0",
          "date": "2026-03-31T00:00:00.000Z",
          "price": 3.619,
          "volume": 22
        },
        {
          "label": "Mar 31 2026 13: +0",
          "date": "2026-03-31T00:00:00.000Z",
          "price": 3.59,
          "volume": 4
        },
        {
          "label": "Mar 31 2026 14: +0",
          "date": "2026-03-31T00:00:00.000Z",
          "price": 3.581,
          "volume": 3
        },
        {
          "label": "Mar 31 2026 15: +0",
          "date": "2026-03-31T00:00:00.000Z",
          "price": 3.581,
          "volume": 2
        },
        {
          "label": "Mar 31 2026 16: +0",
          "date": "2026-03-31T00:00:00.000Z",
          "price": 3.587,
          "volume": 6
        },
        {
          "label": "Mar 31 2026 17: +0",
          "date": "2026-03-31T00:00:00.000Z",
          "price": 3.581,
          "volume": 3
        },
        {
          "label": "Mar 31 2026 18: +0",
          "date": "2026-03-31T00:00:00.000Z",
          "price": 3.586,
          "volume": 4
        },
        {
          "label": "Mar 31 2026 19: +0",
          "date": "2026-03-31T00:00:00.000Z",
          "price": 3.563,
          "volume": 3
        },
        {
          "label": "Mar 31 2026 20: +0",
          "date": "2026-03-31T00:00:00.000Z",
          "price": 3.576,
          "volume": 11
        },
        {
          "label": "Mar 31 2026 22: +0",
          "date": "2026-03-31T00:00:00.000Z",
          "price": 3.139,
          "volume": 3
        },
        {
          "label": "Mar 31 2026 23: +0",
          "date": "2026-03-31T00:00:00.000Z",
          "price": 3.529,
          "volume": 1
        },
        {
          "label": "Apr 01 2026 00: +0",
          "date": "2026-04-01T00:00:00.000Z",
          "price": 3.569,
          "volume": 2
        },
        {
          "label": "Apr 01 2026 03: +0",
          "date": "2026-04-01T00:00:00.000Z",
          "price": 3.587,
          "volume": 1
        },
        {
          "label": "Apr 01 2026 04: +0",
          "date": "2026-04-01T00:00:00.000Z",
          "price": 3.587,
          "volume": 22
        },
        {
          "label": "Apr 01 2026 07: +0",
          "date": "2026-04-01T00:00:00.000Z",
          "price": 3.587,
          "volume": 3
        },
        {
          "label": "Apr 01 2026 08: +0",
          "date": "2026-04-01T00:00:00.000Z",
          "price": 3.58,
          "volume": 3
        },
        {
          "label": "Apr 01 2026 09: +0",
          "date": "2026-04-01T00:00:00.000Z",
          "price": 3.591,
          "volume": 7
        },
        {
          "label": "Apr 01 2026 10: +0",
          "date": "2026-04-01T00:00:00.000Z",
          "price": 3.58,
          "volume": 1
        },
        {
          "label": "Apr 01 2026 11: +0",
          "date": "2026-04-01T00:00:00.000Z",
          "price": 3.589,
          "volume": 4
        },
        {
          "label": "Apr 01 2026 12: +0",
          "date": "2026-04-01T00:00:00.000Z",
          "price": 3.589,
          "volume": 4
        },
        {
          "label": "Apr 01 2026 13: +0",
          "date": "2026-04-01T00:00:00.000Z",
          "price": 3.59,
          "volume": 92
        },
        {
          "label": "Apr 01 2026 14: +0",
          "date": "2026-04-01T00:00:00.000Z",
          "price": 3.544,
          "volume": 3
        },
        {
          "label": "Apr 01 2026 15: +0",
          "date": "2026-04-01T00:00:00.000Z",
          "price": 3.533,
          "volume": 5
        },
        {
          "label": "Apr 01 2026 16: +0",
          "date": "2026-04-01T00:00:00.000Z",
          "price": 3.536,
          "volume": 5
        },
        {
          "label": "Apr 01 2026 17: +0",
          "date": "2026-04-01T00:00:00.000Z",
          "price": 3.54,
          "volume": 1
        },
        {
          "label": "Apr 01 2026 18: +0",
          "date": "2026-04-01T00:00:00.000Z",
          "price": 3.545,
          "volume": 8
        },
        {
          "label": "Apr 01 2026 19: +0",
          "date": "2026-04-01T00:00:00.000Z",
          "price": 3.544,
          "volume": 1
        },
        {
          "label": "Apr 01 2026 20: +0",
          "date": "2026-04-01T00:00:00.000Z",
          "price": 3.521,
          "volume": 4
        },
        {
          "label": "Apr 01 2026 21: +0",
          "date": "2026-04-01T00:00:00.000Z",
          "price": 3.542,
          "volume": 8
        },
        {
          "label": "Apr 01 2026 22: +0",
          "date": "2026-04-01T00:00:00.000Z",
          "price": 3.54,
          "volume": 7
        },
        {
          "label": "Apr 01 2026 23: +0",
          "date": "2026-04-01T00:00:00.000Z",
          "price": 3.52,
          "volume": 27
        },
        {
          "label": "Apr 02 2026 00: +0",
          "date": "2026-04-02T00:00:00.000Z",
          "price": 3.525,
          "volume": 21
        },
        {
          "label": "Apr 02 2026 01: +0",
          "date": "2026-04-02T00:00:00.000Z",
          "price": 3.529,
          "volume": 3
        },
        {
          "label": "Apr 02 2026 02: +0",
          "date": "2026-04-02T00:00:00.000Z",
          "price": 3.52,
          "volume": 4
        },
        {
          "label": "Apr 02 2026 03: +0",
          "date": "2026-04-02T00:00:00.000Z",
          "price": 3.52,
          "volume": 3
        },
        {
          "label": "Apr 02 2026 06: +0",
          "date": "2026-04-02T00:00:00.000Z",
          "price": 3.52,
          "volume": 2
        },
        {
          "label": "Apr 02 2026 07: +0",
          "date": "2026-04-02T00:00:00.000Z",
          "price": 3.053,
          "volume": 1
        },
        {
          "label": "Apr 02 2026 08: +0",
          "date": "2026-04-02T00:00:00.000Z",
          "price": 3.52,
          "volume": 16
        },
        {
          "label": "Apr 02 2026 09: +0",
          "date": "2026-04-02T00:00:00.000Z",
          "price": 3.52,
          "volume": 2
        },
        {
          "label": "Apr 02 2026 10: +0",
          "date": "2026-04-02T00:00:00.000Z",
          "price": 3.52,
          "volume": 1
        },
        {
          "label": "Apr 02 2026 11: +0",
          "date": "2026-04-02T00:00:00.000Z",
          "price": 3.483,
          "volume": 5
        },
        {
          "label": "Apr 02 2026 12: +0",
          "date": "2026-04-02T00:00:00.000Z",
          "price": 3.519,
          "volume": 4
        },
        {
          "label": "Apr 02 2026 13: +0",
          "date": "2026-04-02T00:00:00.000Z",
          "price": 3.519,
          "volume": 6
        },
        {
          "label": "Apr 02 2026 14: +0",
          "date": "2026-04-02T00:00:00.000Z",
          "price": 3.526,
          "volume": 6
        },
        {
          "label": "Apr 02 2026 15: +0",
          "date": "2026-04-02T00:00:00.000Z",
          "price": 3.529,
          "volume": 1
        },
        {
          "label": "Apr 02 2026 17: +0",
          "date": "2026-04-02T00:00:00.000Z",
          "price": 3.526,
          "volume": 9
        },
        {
          "label": "Apr 02 2026 18: +0",
          "date": "2026-04-02T00:00:00.000Z",
          "price": 3.522,
          "volume": 10
        },
        {
          "label": "Apr 02 2026 19: +0",
          "date": "2026-04-02T00:00:00.000Z",
          "price": 3.49,
          "volume": 5
        },
        {
          "label": "Apr 02 2026 20: +0",
          "date": "2026-04-02T00:00:00.000Z",
          "price": 3.529,
          "volume": 1
        },
        {
          "label": "Apr 02 2026 21: +0",
          "date": "2026-04-02T00:00:00.000Z",
          "price": 3.52,
          "volume": 5
        },
        {
          "label": "Apr 02 2026 22: +0",
          "date": "2026-04-02T00:00:00.000Z",
          "price": 3.517,
          "volume": 2
        },
        {
          "label": "Apr 02 2026 23: +0",
          "date": "2026-04-02T00:00:00.000Z",
          "price": 3.52,
          "volume": 20
        },
        {
          "label": "Apr 03 2026 00: +0",
          "date": "2026-04-03T00:00:00.000Z",
          "price": 3.52,
          "volume": 15
        },
        {
          "label": "Apr 03 2026 01: +0",
          "date": "2026-04-03T00:00:00.000Z",
          "price": 3.52,
          "volume": 9
        },
        {
          "label": "Apr 03 2026 03: +0",
          "date": "2026-04-03T00:00:00.000Z",
          "price": 3.52,
          "volume": 4
        },
        {
          "label": "Apr 03 2026 04: +0",
          "date": "2026-04-03T00:00:00.000Z",
          "price": 3.518,
          "volume": 1
        },
        {
          "label": "Apr 03 2026 05: +0",
          "date": "2026-04-03T00:00:00.000Z",
          "price": 3.52,
          "volume": 17
        },
        {
          "label": "Apr 03 2026 07: +0",
          "date": "2026-04-03T00:00:00.000Z",
          "price": 3.523,
          "volume": 9
        },
        {
          "label": "Apr 03 2026 08: +0",
          "date": "2026-04-03T00:00:00.000Z",
          "price": 3.19,
          "volume": 5
        },
        {
          "label": "Apr 03 2026 09: +0",
          "date": "2026-04-03T00:00:00.000Z",
          "price": 3.558,
          "volume": 4
        },
        {
          "label": "Apr 03 2026 10: +0",
          "date": "2026-04-03T00:00:00.000Z",
          "price": 3.518,
          "volume": 6
        },
        {
          "label": "Apr 03 2026 12: +0",
          "date": "2026-04-03T00:00:00.000Z",
          "price": 3.522,
          "volume": 7
        },
        {
          "label": "Apr 03 2026 14: +0",
          "date": "2026-04-03T00:00:00.000Z",
          "price": 3.525,
          "volume": 11
        },
        {
          "label": "Apr 03 2026 15: +0",
          "date": "2026-04-03T00:00:00.000Z",
          "price": 3.528,
          "volume": 4
        },
        {
          "label": "Apr 03 2026 16: +0",
          "date": "2026-04-03T00:00:00.000Z",
          "price": 3.589,
          "volume": 3
        },
        {
          "label": "Apr 03 2026 17: +0",
          "date": "2026-04-03T00:00:00.000Z",
          "price": 3.589,
          "volume": 6
        },
        {
          "label": "Apr 03 2026 18: +0",
          "date": "2026-04-03T00:00:00.000Z",
          "price": 3.589,
          "volume": 1
        },
        {
          "label": "Apr 03 2026 20: +0",
          "date": "2026-04-03T00:00:00.000Z",
          "price": 3.583,
          "volume": 4
        },
        {
          "label": "Apr 03 2026 21: +0",
          "date": "2026-04-03T00:00:00.000Z",
          "price": 3.597,
          "volume": 3
        },
        {
          "label": "Apr 03 2026 22: +0",
          "date": "2026-04-03T00:00:00.000Z",
          "price": 3.585,
          "volume": 7
        },
        {
          "label": "Apr 03 2026 23: +0",
          "date": "2026-04-03T00:00:00.000Z",
          "price": 3.586,
          "volume": 38
        },
        {
          "label": "Apr 04 2026 01: +0",
          "date": "2026-04-04T00:00:00.000Z",
          "price": 3.622,
          "volume": 22
        },
        {
          "label": "Apr 04 2026 02: +0",
          "date": "2026-04-04T00:00:00.000Z",
          "price": 3.607,
          "volume": 1
        },
        {
          "label": "Apr 04 2026 03: +0",
          "date": "2026-04-04T00:00:00.000Z",
          "price": 3.61,
          "volume": 15
        },
        {
          "label": "Apr 04 2026 04: +0",
          "date": "2026-04-04T00:00:00.000Z",
          "price": 3.614,
          "volume": 1
        },
        {
          "label": "Apr 04 2026 05: +0",
          "date": "2026-04-04T00:00:00.000Z",
          "price": 3.606,
          "volume": 2
        },
        {
          "label": "Apr 04 2026 06: +0",
          "date": "2026-04-04T00:00:00.000Z",
          "price": 3.614,
          "volume": 2
        },
        {
          "label": "Apr 04 2026 09: +0",
          "date": "2026-04-04T00:00:00.000Z",
          "price": 3.608,
          "volume": 3
        },
        {
          "label": "Apr 04 2026 10: +0",
          "date": "2026-04-04T00:00:00.000Z",
          "price": 3.608,
          "volume": 3
        },
        {
          "label": "Apr 04 2026 11: +0",
          "date": "2026-04-04T00:00:00.000Z",
          "price": 3.59,
          "volume": 1
        },
        {
          "label": "Apr 04 2026 12: +0",
          "date": "2026-04-04T00:00:00.000Z",
          "price": 3.596,
          "volume": 2
        },
        {
          "label": "Apr 04 2026 13: +0",
          "date": "2026-04-04T00:00:00.000Z",
          "price": 3.596,
          "volume": 5
        },
        {
          "label": "Apr 04 2026 14: +0",
          "date": "2026-04-04T00:00:00.000Z",
          "price": 3.595,
          "volume": 2
        },
        {
          "label": "Apr 04 2026 15: +0",
          "date": "2026-04-04T00:00:00.000Z",
          "price": 3.608,
          "volume": 22
        },
        {
          "label": "Apr 04 2026 17: +0",
          "date": "2026-04-04T00:00:00.000Z",
          "price": 3.621,
          "volume": 1
        },
        {
          "label": "Apr 04 2026 18: +0",
          "date": "2026-04-04T00:00:00.000Z",
          "price": 3.623,
          "volume": 3
        },
        {
          "label": "Apr 04 2026 19: +0",
          "date": "2026-04-04T00:00:00.000Z",
          "price": 3.642,
          "volume": 1
        },
        {
          "label": "Apr 04 2026 22: +0",
          "date": "2026-04-04T00:00:00.000Z",
          "price": 3.28,
          "volume": 1
        },
        {
          "label": "Apr 04 2026 23: +0",
          "date": "2026-04-04T00:00:00.000Z",
          "price": 3.615,
          "volume": 11
        },
        {
          "label": "Apr 05 2026 00: +0",
          "date": "2026-04-05T00:00:00.000Z",
          "price": 3.61,
          "volume": 15
        },
        {
          "label": "Apr 05 2026 01: +0",
          "date": "2026-04-05T00:00:00.000Z",
          "price": 3.622,
          "volume": 121
        },
        {
          "label": "Apr 05 2026 02: +0",
          "date": "2026-04-05T00:00:00.000Z",
          "price": 3.46,
          "volume": 2
        },
        {
          "label": "Apr 05 2026 03: +0",
          "date": "2026-04-05T00:00:00.000Z",
          "price": 3.61,
          "volume": 15
        },
        {
          "label": "Apr 05 2026 04: +0",
          "date": "2026-04-05T00:00:00.000Z",
          "price": 3.592,
          "volume": 3
        },
        {
          "label": "Apr 05 2026 05: +0",
          "date": "2026-04-05T00:00:00.000Z",
          "price": 3.59,
          "volume": 6
        },
        {
          "label": "Apr 05 2026 06: +0",
          "date": "2026-04-05T00:00:00.000Z",
          "price": 3.613,
          "volume": 7
        },
        {
          "label": "Apr 05 2026 07: +0",
          "date": "2026-04-05T00:00:00.000Z",
          "price": 3.623,
          "volume": 22
        },
        {
          "label": "Apr 05 2026 08: +0",
          "date": "2026-04-05T00:00:00.000Z",
          "price": 3.61,
          "volume": 18
        },
        {
          "label": "Apr 05 2026 10: +0",
          "date": "2026-04-05T00:00:00.000Z",
          "price": 3.623,
          "volume": 1
        },
        {
          "label": "Apr 05 2026 11: +0",
          "date": "2026-04-05T00:00:00.000Z",
          "price": 3.62,
          "volume": 13
        },
        {
          "label": "Apr 05 2026 12: +0",
          "date": "2026-04-05T00:00:00.000Z",
          "price": 3.542,
          "volume": 2
        },
        {
          "label": "Apr 05 2026 13: +0",
          "date": "2026-04-05T00:00:00.000Z",
          "price": 3.563,
          "volume": 2
        },
        {
          "label": "Apr 05 2026 14: +0",
          "date": "2026-04-05T00:00:00.000Z",
          "price": 3.606,
          "volume": 16
        },
        {
          "label": "Apr 05 2026 15: +0",
          "date": "2026-04-05T00:00:00.000Z",
          "price": 3.621,
          "volume": 47
        },
        {
          "label": "Apr 05 2026 16: +0",
          "date": "2026-04-05T00:00:00.000Z",
          "price": 3.61,
          "volume": 3
        },
        {
          "label": "Apr 05 2026 17: +0",
          "date": "2026-04-05T00:00:00.000Z",
          "price": 3.622,
          "volume": 10
        },
        {
          "label": "Apr 05 2026 18: +0",
          "date": "2026-04-05T00:00:00.000Z",
          "price": 3.61,
          "volume": 12
        },
        {
          "label": "Apr 05 2026 19: +0",
          "date": "2026-04-05T00:00:00.000Z",
          "price": 3.62,
          "volume": 3
        },
        {
          "label": "Apr 05 2026 20: +0",
          "date": "2026-04-05T00:00:00.000Z",
          "price": 3.447,
          "volume": 6
        },
        {
          "label": "Apr 05 2026 22: +0",
          "date": "2026-04-05T00:00:00.000Z",
          "price": 3.608,
          "volume": 6
        },
        {
          "label": "Apr 05 2026 23: +0",
          "date": "2026-04-05T00:00:00.000Z",
          "price": 3.6,
          "volume": 20
        },
        {
          "label": "Apr 06 2026 01: +0",
          "date": "2026-04-06T00:00:00.000Z",
          "price": 3.61,
          "volume": 3
        },
        {
          "label": "Apr 06 2026 03: +0",
          "date": "2026-04-06T00:00:00.000Z",
          "price": 3.621,
          "volume": 1
        },
        {
          "label": "Apr 06 2026 04: +0",
          "date": "2026-04-06T00:00:00.000Z",
          "price": 3.61,
          "volume": 1
        },
        {
          "label": "Apr 06 2026 05: +0",
          "date": "2026-04-06T00:00:00.000Z",
          "price": 3.61,
          "volume": 3
        },
        {
          "label": "Apr 06 2026 08: +0",
          "date": "2026-04-06T00:00:00.000Z",
          "price": 3.6,
          "volume": 3
        },
        {
          "label": "Apr 06 2026 09: +0",
          "date": "2026-04-06T00:00:00.000Z",
          "price": 3.603,
          "volume": 2
        },
        {
          "label": "Apr 06 2026 11: +0",
          "date": "2026-04-06T00:00:00.000Z",
          "price": 3.609,
          "volume": 3
        },
        {
          "label": "Apr 06 2026 12: +0",
          "date": "2026-04-06T00:00:00.000Z",
          "price": 3.599,
          "volume": 1
        },
        {
          "label": "Apr 06 2026 13: +0",
          "date": "2026-04-06T00:00:00.000Z",
          "price": 3.597,
          "volume": 13
        },
        {
          "label": "Apr 06 2026 14: +0",
          "date": "2026-04-06T00:00:00.000Z",
          "price": 3.597,
          "volume": 5
        },
        {
          "label": "Apr 06 2026 15: +0",
          "date": "2026-04-06T00:00:00.000Z",
          "price": 3.601,
          "volume": 4
        },
        {
          "label": "Apr 06 2026 16: +0",
          "date": "2026-04-06T00:00:00.000Z",
          "price": 3.597,
          "volume": 9
        },
        {
          "label": "Apr 06 2026 17: +0",
          "date": "2026-04-06T00:00:00.000Z",
          "price": 3.609,
          "volume": 2
        },
        {
          "label": "Apr 06 2026 18: +0",
          "date": "2026-04-06T00:00:00.000Z",
          "price": 3.62,
          "volume": 1
        },
        {
          "label": "Apr 06 2026 19: +0",
          "date": "2026-04-06T00:00:00.000Z",
          "price": 3.293,
          "volume": 4
        },
        {
          "label": "Apr 06 2026 20: +0",
          "date": "2026-04-06T00:00:00.000Z",
          "price": 3.608,
          "volume": 1
        },
        {
          "label": "Apr 06 2026 21: +0",
          "date": "2026-04-06T00:00:00.000Z",
          "price": 3.61,
          "volume": 5
        },
        {
          "label": "Apr 06 2026 23: +0",
          "date": "2026-04-06T00:00:00.000Z",
          "price": 3.627,
          "volume": 1
        },
        {
          "label": "Apr 07 2026 00: +0",
          "date": "2026-04-07T00:00:00.000Z",
          "price": 3.65,
          "volume": 1
        },
        {
          "label": "Apr 07 2026 01: +0",
          "date": "2026-04-07T00:00:00.000Z",
          "price": 3.664,
          "volume": 12
        },
        {
          "label": "Apr 07 2026 04: +0",
          "date": "2026-04-07T00:00:00.000Z",
          "price": 3.65,
          "volume": 4
        },
        {
          "label": "Apr 07 2026 06: +0",
          "date": "2026-04-07T00:00:00.000Z",
          "price": 3.674,
          "volume": 1
        },
        {
          "label": "Apr 07 2026 10: +0",
          "date": "2026-04-07T00:00:00.000Z",
          "price": 3.662,
          "volume": 1
        },
        {
          "label": "Apr 07 2026 11: +0",
          "date": "2026-04-07T00:00:00.000Z",
          "price": 3.674,
          "volume": 31
        },
        {
          "label": "Apr 07 2026 12: +0",
          "date": "2026-04-07T00:00:00.000Z",
          "price": 3.352,
          "volume": 22
        },
        {
          "label": "Apr 07 2026 13: +0",
          "date": "2026-04-07T00:00:00.000Z",
          "price": 3.668,
          "volume": 5
        },
        {
          "label": "Apr 07 2026 14: +0",
          "date": "2026-04-07T00:00:00.000Z",
          "price": 3.655,
          "volume": 2
        },
        {
          "label": "Apr 07 2026 15: +0",
          "date": "2026-04-07T00:00:00.000Z",
          "price": 3.667,
          "volume": 11
        },
        {
          "label": "Apr 07 2026 17: +0",
          "date": "2026-04-07T00:00:00.000Z",
          "price": 3.651,
          "volume": 6
        },
        {
          "label": "Apr 07 2026 18: +0",
          "date": "2026-04-07T00:00:00.000Z",
          "price": 3.665,
          "volume": 21
        },
        {
          "label": "Apr 07 2026 19: +0",
          "date": "2026-04-07T00:00:00.000Z",
          "price": 3.651,
          "volume": 8
        },
        {
          "label": "Apr 07 2026 20: +0",
          "date": "2026-04-07T00:00:00.000Z",
          "price": 3.651,
          "volume": 6
        },
        {
          "label": "Apr 07 2026 21: +0",
          "date": "2026-04-07T00:00:00.000Z",
          "price": 3.65,
          "volume": 2
        },
        {
          "label": "Apr 07 2026 22: +0",
          "date": "2026-04-07T00:00:00.000Z",
          "price": 3.654,
          "volume": 3
        },
        {
          "label": "Apr 08 2026 00: +0",
          "date": "2026-04-08T00:00:00.000Z",
          "price": 3.676,
          "volume": 3
        },
        {
          "label": "Apr 08 2026 02: +0",
          "date": "2026-04-08T00:00:00.000Z",
          "price": 3.66,
          "volume": 3
        },
        {
          "label": "Apr 08 2026 07: +0",
          "date": "2026-04-08T00:00:00.000Z",
          "price": 3.65,
          "volume": 11
        },
        {
          "label": "Apr 08 2026 08: +0",
          "date": "2026-04-08T00:00:00.000Z",
          "price": 3.66,
          "volume": 13
        },
        {
          "label": "Apr 08 2026 09: +0",
          "date": "2026-04-08T00:00:00.000Z",
          "price": 3.653,
          "volume": 5
        },
        {
          "label": "Apr 08 2026 10: +0",
          "date": "2026-04-08T00:00:00.000Z",
          "price": 3.653,
          "volume": 1
        },
        {
          "label": "Apr 08 2026 11: +0",
          "date": "2026-04-08T00:00:00.000Z",
          "price": 3.66,
          "volume": 7
        },
        {
          "label": "Apr 08 2026 12: +0",
          "date": "2026-04-08T00:00:00.000Z",
          "price": 3.642,
          "volume": 10
        },
        {
          "label": "Apr 08 2026 13: +0",
          "date": "2026-04-08T00:00:00.000Z",
          "price": 3.584,
          "volume": 1
        },
        {
          "label": "Apr 08 2026 14: +0",
          "date": "2026-04-08T00:00:00.000Z",
          "price": 3.676,
          "volume": 29
        },
        {
          "label": "Apr 08 2026 15: +0",
          "date": "2026-04-08T00:00:00.000Z",
          "price": 3.656,
          "volume": 8
        },
        {
          "label": "Apr 08 2026 16: +0",
          "date": "2026-04-08T00:00:00.000Z",
          "price": 3.492,
          "volume": 1
        },
        {
          "label": "Apr 08 2026 17: +0",
          "date": "2026-04-08T00:00:00.000Z",
          "price": 3.403,
          "volume": 5
        },
        {
          "label": "Apr 08 2026 18: +0",
          "date": "2026-04-08T00:00:00.000Z",
          "price": 3.642,
          "volume": 3
        },
        {
          "label": "Apr 08 2026 19: +0",
          "date": "2026-04-08T00:00:00.000Z",
          "price": 3.653,
          "volume": 22
        },
        {
          "label": "Apr 08 2026 20: +0",
          "date": "2026-04-08T00:00:00.000Z",
          "price": 3.669,
          "volume": 3
        },
        {
          "label": "Apr 08 2026 21: +0",
          "date": "2026-04-08T00:00:00.000Z",
          "price": 3.725,
          "volume": 4
        },
        {
          "label": "Apr 09 2026 00: +0",
          "date": "2026-04-09T00:00:00.000Z",
          "price": 3.7,
          "volume": 38
        },
        {
          "label": "Apr 09 2026 02: +0",
          "date": "2026-04-09T00:00:00.000Z",
          "price": 3.7,
          "volume": 2
        },
        {
          "label": "Apr 09 2026 04: +0",
          "date": "2026-04-09T00:00:00.000Z",
          "price": 3.521,
          "volume": 2
        },
        {
          "label": "Apr 09 2026 07: +0",
          "date": "2026-04-09T00:00:00.000Z",
          "price": 3.694,
          "volume": 1
        },
        {
          "label": "Apr 09 2026 09: +0",
          "date": "2026-04-09T00:00:00.000Z",
          "price": 3.698,
          "volume": 2
        },
        {
          "label": "Apr 09 2026 13: +0",
          "date": "2026-04-09T00:00:00.000Z",
          "price": 3.698,
          "volume": 10
        },
        {
          "label": "Apr 09 2026 14: +0",
          "date": "2026-04-09T00:00:00.000Z",
          "price": 3.698,
          "volume": 3
        },
        {
          "label": "Apr 09 2026 15: +0",
          "date": "2026-04-09T00:00:00.000Z",
          "price": 3.4,
          "volume": 11
        },
        {
          "label": "Apr 09 2026 16: +0",
          "date": "2026-04-09T00:00:00.000Z",
          "price": 3.408,
          "volume": 5
        },
        {
          "label": "Apr 09 2026 17: +0",
          "date": "2026-04-09T00:00:00.000Z",
          "price": 3.699,
          "volume": 3
        },
        {
          "label": "Apr 09 2026 18: +0",
          "date": "2026-04-09T00:00:00.000Z",
          "price": 3.7,
          "volume": 15
        },
        {
          "label": "Apr 09 2026 20: +0",
          "date": "2026-04-09T00:00:00.000Z",
          "price": 3.51,
          "volume": 23
        },
        {
          "label": "Apr 09 2026 21: +0",
          "date": "2026-04-09T00:00:00.000Z",
          "price": 3.51,
          "volume": 7
        }
      ]
    }
  },
  "errors": [
    {
      "name": "Falchion Case",
      "reason": "Steam listing failed (429) for Falchion Case"
    },
    {
      "name": "Winter Offensive Weapon Case",
      "reason": "Steam listing failed (429) for Winter Offensive Weapon Case"
    },
    {
      "name": "Operation Phoenix Weapon Case",
      "reason": "Steam listing failed (429) for Operation Phoenix Weapon Case"
    },
    {
      "name": "Chroma Case",
      "reason": "Steam listing failed (429) for Chroma Case"
    },
    {
      "name": "Horizon Case",
      "reason": "Steam listing failed (429) for Horizon Case"
    },
    {
      "name": "Snakebite Case",
      "reason": "Steam listing failed (429) for Snakebite Case"
    },
    {
      "name": "Spectrum Case",
      "reason": "Steam listing failed (429) for Spectrum Case"
    },
    {
      "name": "Operation Breakout Weapon Case",
      "reason": "Steam listing failed (429) for Operation Breakout Weapon Case"
    },
    {
      "name": "Spectrum 2 Case",
      "reason": "Steam listing failed (429) for Spectrum 2 Case"
    },
    {
      "name": "Prisma 2 Case",
      "reason": "Steam listing failed (429) for Prisma 2 Case"
    },
    {
      "name": "Shadow Case",
      "reason": "Steam listing failed (429) for Shadow Case"
    },
    {
      "name": "Chroma 2 Case",
      "reason": "Steam listing failed (429) for Chroma 2 Case"
    },
    {
      "name": "Glove Case",
      "reason": "Steam listing failed (429) for Glove Case"
    },
    {
      "name": "Danger Zone Case",
      "reason": "Steam listing failed (429) for Danger Zone Case"
    },
    {
      "name": "Clutch Case",
      "reason": "Steam listing failed (429) for Clutch Case"
    },
    {
      "name": "Prisma Case",
      "reason": "Steam listing failed (429) for Prisma Case"
    },
    {
      "name": "Huntsman Weapon Case",
      "reason": "Steam listing failed (429) for Huntsman Weapon Case"
    },
    {
      "name": "Revolver Case",
      "reason": "Steam listing failed (429) for Revolver Case"
    },
    {
      "name": "Gamma Case",
      "reason": "Steam listing failed (429) for Gamma Case"
    },
    {
      "name": "CS20 Case",
      "reason": "Steam listing failed (429) for CS20 Case"
    },
    {
      "name": "Gamma 2 Case",
      "reason": "Steam listing failed (429) for Gamma 2 Case"
    },
    {
      "name": "Chroma 3 Case",
      "reason": "Steam listing failed (429) for Chroma 3 Case"
    },
    {
      "name": "Operation Vanguard Weapon Case",
      "reason": "Steam listing failed (429) for Operation Vanguard Weapon Case"
    },
    {
      "name": "Operation Wildfire Case",
      "reason": "Steam listing failed (429) for Operation Wildfire Case"
    },
    {
      "name": "Dreams & Nightmares Case",
      "reason": "Steam listing failed (429) for Dreams & Nightmares Case"
    },
    {
      "name": "Fracture Case",
      "reason": "Steam listing failed (429) for Fracture Case"
    },
    {
      "name": "Recoil Case",
      "reason": "Steam listing failed (429) for Recoil Case"
    },
    {
      "name": "Revolution Case",
      "reason": "Steam listing failed (429) for Revolution Case"
    },
    {
      "name": "Kilowatt Case",
      "reason": "Steam listing failed (429) for Kilowatt Case"
    },
    {
      "name": "Fever Case",
      "reason": "Steam listing failed (429) for Fever Case"
    },
    {
      "name": "CS:GO Weapon Case",
      "reason": "Steam listing failed (429) for CS:GO Weapon Case"
    },
    {
      "name": "Operation Broken Fang Case",
      "reason": "Steam listing failed (429) for Operation Broken Fang Case"
    },
    {
      "name": "eSports 2013 Winter Case",
      "reason": "Steam listing failed (429) for eSports 2013 Winter Case"
    },
    {
      "name": "Gallery Case",
      "reason": "Steam listing failed (429) for Gallery Case"
    },
    {
      "name": "Operation Bravo Case",
      "reason": "Steam listing failed (429) for Operation Bravo Case"
    },
    {
      "name": "eSports 2014 Summer Case",
      "reason": "Steam listing failed (429) for eSports 2014 Summer Case"
    },
    {
      "name": "Operation Hydra Case",
      "reason": "Steam listing failed (429) for Operation Hydra Case"
    },
    {
      "name": "Operation Riptide Case",
      "reason": "Steam listing failed (429) for Operation Riptide Case"
    },
    {
      "name": "Shattered Web Case",
      "reason": "Steam listing failed (429) for Shattered Web Case"
    },
    {
      "name": "Anubis Collection Package",
      "reason": "Steam listing failed (429) for Anubis Collection Package"
    },
    {
      "name": "CS:GO Weapon Case 2",
      "reason": "Steam listing failed (429) for CS:GO Weapon Case 2"
    },
    {
      "name": "CS:GO Weapon Case 3",
      "reason": "Steam listing failed (429) for CS:GO Weapon Case 3"
    },
    {
      "name": "Sticker Capsule 2",
      "reason": "Steam listing failed (429) for Sticker Capsule 2"
    },
    {
      "name": "Stockholm 2021 Legends Sticker Capsule",
      "reason": "Steam listing failed (429) for Stockholm 2021 Legends Sticker Capsule"
    },
    {
      "name": "Sealed Genesis Terminal",
      "reason": "Steam listing failed (429) for Sealed Genesis Terminal"
    },
    {
      "name": "eSports 2013 Case",
      "reason": "Steam listing failed (429) for eSports 2013 Case"
    },
    {
      "name": "Paris 2023 Mirage Souvenir Package",
      "reason": "Steam listing failed (429) for Paris 2023 Mirage Souvenir Package"
    },
    {
      "name": "Sealed Dead Hand Terminal",
      "reason": "Steam listing failed (429) for Sealed Dead Hand Terminal"
    }
  ]
}